odoo/addons/sale_coupon_auto_refresh/README.rst
odoo/addons/sale_coupon_auto_refresh/__init__.py
odoo/addons/sale_coupon_auto_refresh/__manifest__.py
odoo/addons/sale_coupon_auto_refresh/i18n/es.po
odoo/addons/sale_coupon_auto_refresh/i18n/fr.po
odoo/addons/sale_coupon_auto_refresh/i18n/it.po
odoo/addons/sale_coupon_auto_refresh/i18n/sale_coupon_auto_refresh.pot
odoo/addons/sale_coupon_auto_refresh/i18n/zh_CN.po
odoo/addons/sale_coupon_auto_refresh/models/__init__.py
odoo/addons/sale_coupon_auto_refresh/models/res_company.py
odoo/addons/sale_coupon_auto_refresh/models/res_config_settings.py
odoo/addons/sale_coupon_auto_refresh/models/sale_coupon_refresh_mixin.py
odoo/addons/sale_coupon_auto_refresh/models/sale_order.py
odoo/addons/sale_coupon_auto_refresh/readme/CONFIGURE.rst
odoo/addons/sale_coupon_auto_refresh/readme/CONTRIBUTORS.rst
odoo/addons/sale_coupon_auto_refresh/readme/DESCRIPTION.rst
odoo/addons/sale_coupon_auto_refresh/readme/ROADMAP.rst
odoo/addons/sale_coupon_auto_refresh/readme/USAGE.rst
odoo/addons/sale_coupon_auto_refresh/static/description/icon.png
odoo/addons/sale_coupon_auto_refresh/static/description/index.html
odoo/addons/sale_coupon_auto_refresh/tests/__init__.py
odoo/addons/sale_coupon_auto_refresh/tests/test_sale_coupon_auto_refresh.py
odoo/addons/sale_coupon_auto_refresh/views/res_config_settings_views.xml
odoo/addons/sale_coupon_auto_refresh/wizard/__init__.py
odoo/addons/sale_coupon_auto_refresh/wizard/sale_coupon_apply_code.py
odoo14_addon_sale_coupon_auto_refresh-14.0.2.0.1.dist-info/METADATA
odoo14_addon_sale_coupon_auto_refresh-14.0.2.0.1.dist-info/WHEEL
odoo14_addon_sale_coupon_auto_refresh-14.0.2.0.1.dist-info/top_level.txt
odoo14_addon_sale_coupon_auto_refresh-14.0.2.0.1.dist-info/RECORD
